pybites_tools/__init__.py
pybites_tools/aws.py
pybites_tools/license.py
pybites_tools/meaning.py
pybites_tools/sendemail.py
pybites_tools/worldclock.py
pybites_tools/zen.py
pybites_tools-0.2.dist-info/entry_points.txt
pybites_tools-0.2.dist-info/LICENSE
pybites_tools-0.2.dist-info/WHEEL
pybites_tools-0.2.dist-info/METADATA
pybites_tools-0.2.dist-info/RECORD
