Metadata-Version: 2.1
Name: pybites-tools
Version: 0.2
Summary: Common tools we use as PyBites
Author-email: PyBites <support@pybit.es>
Requires-Python: >=3.7
Classifier: License :: OSI Approved :: MIT License
Requires-Dist: requests >=2.26.0
Requires-Dist: python-dotenv >=0.19.0
Requires-Dist: boto3 >=1.18.36
Requires-Dist: pyperclip >=1.8.2
Requires-Dist: python-dateutil >=2.8.2
Requires-Dist: pytest ; extra == "test"
Requires-Dist: pytest-cov ; extra == "test"
Requires-Dist: mypy ; extra == "test"
Requires-Dist: flake8 ; extra == "test"
Requires-Dist: pre-commit ; extra == "test"
Project-URL: Source, https://github.com/PyBites-Open-Source/pybites-tools
Provides-Extra: test
